README.md
gym_microrts/__init__.py
gym_microrts/envs/__init__.py
gym_microrts/envs/base_env.py
gym_microrts/envs/global_agent_env.py
gym_microrts/envs/local_agent_env.py
gym_microrts/envs/param_op_env.py
gym_microrts/microrts_ai.py
gym_microrts/types.py
gym_microrts/v1.py
gym_microrts/v2.py
microrts/Coac.jar
microrts/maps/.DS_Store
microrts/maps/10x10/basesTwoWorkers10x10.xml
microrts/maps/10x10/basesWorkers10x10.xml
microrts/maps/12x12/FourBasesWorkers12x12.xml
microrts/maps/12x12/OneBaseWorker12x12.xml
microrts/maps/12x12/SixBasesWorkers12x12.xml
microrts/maps/12x12/ThreeBasesWorkers12x12.xml
microrts/maps/12x12/TwoBasesWorkers12x12.xml
microrts/maps/12x12/basesWorkers12x12.xml
microrts/maps/12x12/basesWorkers12x12A.xml
microrts/maps/12x12/basesWorkers12x12B.xml
microrts/maps/12x12/basesWorkers12x12C.xml
microrts/maps/12x12/basesWorkers12x12D.xml
microrts/maps/12x12/basesWorkers12x12E.xml
microrts/maps/12x12/basesWorkers12x12F.xml
microrts/maps/12x12/basesWorkers12x12G.xml
microrts/maps/12x12/basesWorkers12x12H.xml
microrts/maps/12x12/basesWorkers12x12I.xml
microrts/maps/12x12/basesWorkers12x12J.xml
microrts/maps/12x12/basesWorkers12x12K.xml
microrts/maps/12x12/basesWorkers12x12L.xml
microrts/maps/12x12/complexBasesWorkers12x12.xml
microrts/maps/12x12/melee12x12Mixed12.xml
microrts/maps/16x16/EightBasesWorkers16x16.xml
microrts/maps/16x16/TwoBasesBarracks16x16.xml
microrts/maps/16x16/basesWorkers16x16.xml
microrts/maps/16x16/basesWorkers16x16A.xml
microrts/maps/16x16/basesWorkers16x16B.xml
microrts/maps/16x16/basesWorkers16x16C.xml
microrts/maps/16x16/basesWorkers16x16D.xml
microrts/maps/16x16/basesWorkers16x16E.xml
microrts/maps/16x16/basesWorkers16x16F.xml
microrts/maps/16x16/basesWorkers16x16G.xml
microrts/maps/16x16/basesWorkers16x16H.xml
microrts/maps/16x16/basesWorkers16x16I.xml
microrts/maps/16x16/basesWorkers16x16J.xml
microrts/maps/16x16/basesWorkers16x16K.xml
microrts/maps/16x16/basesWorkers16x16L.xml
microrts/maps/16x16/basesWorkers16x16R20.xml
gym_microrts-0.1.3.dist-info/WHEEL
gym_microrts-0.1.3.dist-info/METADATA
gym_microrts-0.1.3.dist-info/RECORD
