Metadata-Version: 2.1
Name: gym-microrts
Version: 0.1.3
Summary: 
Author: Costa Huang
Author-email: costa.huang@outlook.com
Requires-Python: >=3.7,<4.0
Classifier: Programming Language :: Python :: 3
Classifier: Programming Language :: Python :: 3.7
Classifier: Programming Language :: Python :: 3.8
Classifier: Programming Language :: Python :: 3.9
Requires-Dist: JPype1 (>=1.0.2,<2.0.0)
Requires-Dist: Pillow (>=7.2.0,<8.0.0)
Requires-Dist: dacite (>=1.5.1,<2.0.0)
Requires-Dist: gym (>=0.17.3,<0.18.0)
